{
  "$schema": "https://docs.renovatebot.com/renovate-schema.json",
  "description": "Base preset for use with Renovate's repos",
  "extends": [
    "config:base",
    ":dependencyDashboard",
    ":rebaseStalePrs",
    ":semanticCommits",
    ":semanticCommitScope(deps)",
    "docker:enableMajor",
    ":masterIssue",
    "group:linters"
  ],
  "lockFileMaintenance": {
    "enabled": true,
    "automergeType": "branch",
    "dependencyDashboardApproval": false
  },
  "assignees": ["rarkins", "viceice"],
  "prCreation": "not-pending",
  "docker": {
    "pinDigests": true
  },
  "packageRules": [
    {
      "updateTypes": ["major"],
      "dependencyDashboardApproval": true
    },
    {
      "description": "Automerge non-major updates",
      "excludePackageNames": ["renovate"],
      "updateTypes": ["minor", "patch", "digest", "lockFileMaintenance"],
      "automerge": true
    },
    {
      "depTypeList": ["devDependencies"],
      "updateTypes": ["pin", "digest", "patch", "minor"],
      "automerge": true,
      "dependencyDashboardApproval": false
    },
    {
      "description": "Auto aprove any renovate dependencies",
      "packageNames": ["renovate"],
      "packagePatterns": ["^renovate/", "^renovatebot/"],
      "stabilityDays": 0,
      "dependencyDashboardApproval": false
    },
    {
      "description": "Automerge renovate minor and lower updates",
      "packagePatterns": ["^renovate/"],
      "updateTypes": ["pin", "digest", "patch", "minor"],
      "automerge": true,
      "separateMinorPatch": false
    },
    {
      "depTypeList": ["action"],
      "extractVersion": "^(?<version>v\\d+\\.\\d+\\.\\d+)$",
      "versioning": "regex:^v(?<major>\\d+)(\\.(?<minor>\\d+)\\.(?<patch>\\d+))?$"
    },
    {
      "packageNames": ["prettier"],
      "packagePatterns": ["^@prettier\\/", "^prettier-plugin-"],
      "groupName": "prettier packages"
    },
    {
      "description": "Update references to Docker tags for renovate/renovate in Markdown files",
      "packageNames": ["renovate/renovate"],
      "paths": [".md"],
      "extends": ["schedule:weekly"],
      "automerge": true,
      "stabilityDays": 0
    }
  ],
  "regexManagers": [
    {
      "fileMatch": ["\\.md$"],
      "matchStrings": [
        "(?<depName>renovate\\/renovate):(?<currentValue>[a-z0-9.-]+)(?:@(?<currentDigest>sha256:[a-f0-9]+))?"
      ],
      "datasourceTemplate": "docker",
      "versioningTemplate": "docker"
    }
  ]
}
